exoTras/__init__.py
exoTras/env.py
exoTras/exosomes.gmt
exoTras/functional.py
exoTras/id_homo_rna_exo
exoTras/id_mus_rna_exo
exoTras/main.py
exoTras/utils.py
exoTras/version.py
exoTras-0.4.dist-info/LICENSE
exoTras-0.4.dist-info/METADATA
exoTras-0.4.dist-info/WHEEL
exoTras-0.4.dist-info/entry_points.txt
exoTras-0.4.dist-info/top_level.txt
exoTras-0.4.dist-info/RECORD
