Metadata-Version: 2.1
Name: exoTras
Version: 0.4
Summary: exosome-containing droplet identification and source tracking in scRNA-seq data
Home-page: http://pypi.python.org/pypi/exoTras/
Author: Ruiqiao He
Author-email: ruiqiaohe@gmail.com
License: GPL
Classifier: Development Status :: 3 - Alpha
Classifier: License :: OSI Approved :: GNU General Public License v3 (GPLv3)
Classifier: Programming Language :: Python :: 3.7
Classifier: Topic :: Scientific/Engineering :: Bio-Informatics
Requires-Python: >=3.7.1
License-File: LICENSE
Requires-Dist: scanpy (>=1.6.0)
Requires-Dist: numpy (>=1.21.5)
Requires-Dist: pandas (>=1.1.2)
Requires-Dist: scipy (>=1.5.4)
Requires-Dist: statsmodels (>=0.12.1)
Requires-Dist: gseapy
